procurve/__init__.py
procurve/plotting.py
procurve/principal_curve.py
procurve/utils.py
procurve-0.0.2.dist-info/LICENSE
procurve-0.0.2.dist-info/METADATA
procurve-0.0.2.dist-info/WHEEL
procurve-0.0.2.dist-info/top_level.txt
procurve-0.0.2.dist-info/RECORD
