Metadata-Version: 2.1
Name: procurve
Version: 0.0.2
Summary: Principal curve for spherical data using splines.
Author-email: Mauricio Salazar <e.m.salazar.duque@tue.nl>
License: MIT
Project-URL: repository, https://github.com/MauricioSalazare/procurve
Keywords: principal curve,dimensionality reduction
Classifier: Programming Language :: Python :: 3
Classifier: License :: OSI Approved :: MIT License
Classifier: Operating System :: OS Independent
Requires-Python: >=3.0
License-File: LICENSE
Requires-Dist: numpy
Requires-Dist: matplotlib
Requires-Dist: scipy
Provides-Extra: dev
Requires-Dist: build ; extra == 'dev'
Requires-Dist: twine ; extra == 'dev'
Requires-Dist: jupyterlab ; extra == 'dev'
Provides-Extra: doc
Requires-Dist: sphinx ; extra == 'doc'
Provides-Extra: test
Requires-Dist: pytest ; extra == 'test'
